tmux_timer/__init__.py
tmux_timer/command_line.py
tmux_timer-0.1.0.dist-info/DESCRIPTION.rst
tmux_timer-0.1.0.dist-info/METADATA
tmux_timer-0.1.0.dist-info/RECORD
tmux_timer-0.1.0.dist-info/WHEEL
tmux_timer-0.1.0.dist-info/entry_points.txt
tmux_timer-0.1.0.dist-info/metadata.json
tmux_timer-0.1.0.dist-info/top_level.txt
