Metadata-Version: 2.0
Name: tmux-timer
Version: 0.1.0
Summary: Command-line timer for tmux
Home-page: https://github.com/chrahunt/python-tmux-timer
Author: Chris Hunt
Author-email: chrahunt@gmail.com
License: UNKNOWN
Platform: UNKNOWN
Classifier: Environment :: Console
Classifier: License :: OSI Approved :: MIT License
Classifier: Operating System :: POSIX
Classifier: Programming Language :: Python
Requires-Python: >=2.7
